[
{"region":"US","price":13.99,"currency_code":"USD","currency_symbol":"$"},
{"region":"UA","price":163.0,"currency_code":"UAH","currency_symbol":"\u20b4"},
{"region":"PL","price":50.04,"currency_code":"PLN","currency_symbol":"z\u0142"},
{"region":"KZ","price":1656.0,"currency_code":"KZT","currency_symbol":"\u20b8"},
{"region":"KR","price":15680.0,"currency_code":"KRW","currency_symbol":"\u20a9"},
{"region":"BR","price":37.45,"currency_code":"BRL","currency_symbol":"R$"},
{"region":"MX","price":232.75,"currency_code":"MXN","currency_symbol":"Mex$"},
{"region":"IN","price":465.0,"currency_code":"INR","currency_symbol":"\u20b9"},
{"region":"UY","price":279.0,"currency_code":"UYU","currency_symbol":"UYU"},
{"region":"KW","price":2.24,"currency_code":"KWD","currency_symbol":"\u062f.\u0643"},
{"region":"ZA","price":163.1,"currency_code":"ZAR","currency_symbol":"R"},
{"region":"CR","price":5575.0,"currency_code":"CRC","currency_symbol":"\u20a1"},
{"region":"CO","price":43163.0,"currency_code":"COP","currency_symbol":"$"},
{"region":"NO","price":116.55,"currency_code":"NOK","currency_symbol":"kr"},
{"region":"CL","price":10475.0,"currency_code":"CLP","currency_symbol":"$"},
{"region":"VN","price":291500.0,"currency_code":"VND","currency_symbol":"\u20ab"},
{"region":"TH","price":486.5,"currency_code":"THB","currency_symbol":"\u0e3f"},
{"region":"IL","price":52.48,"currency_code":"ILS","currency_symbol":"\u20aa"},
{"region":"SG","price":19.21,"currency_code":"SGD","currency_symbol":"SGD"},
{"region":"PE","price":55.65,"currency_code":"PEN","currency_symbol":"S/"},
{"region":"EU","price":13.99,"currency_code":"EUR","currency_symbol":"\u20ac"},
{"region":"CH","price":16.45,"currency_code":"CHF","currency_symbol":"Fr"},
{"region":"JP","price":1848.0,"currency_code":"JPY","currency_symbol":"\u00a5"},
{"region":"MY","price":59.15,"currency_code":"MYR","currency_symbol":"RM"},
{"region":"PH","price":769.65,"currency_code":"PHP","currency_symbol":"\u20b1"},
{"region":"HK","price":107.8,"currency_code":"HKD","currency_symbol":"HKD"},
{"region":"GB","price":10.49,"currency_code":"GBP","currency_symbol":"\u00a3"},
{"region":"CA","price":18.72,"currency_code":"CAD","currency_symbol":"C$"},
{"region":"TR","price":11.19,"currency_code":"USD","currency_symbol":"$"}
]